{
    "decks": {
        "stater": {
            "cards": [
                7,
                8,
                17,
                19,
                8,
                16,
                18,
                41,
                19,
                17,
                10,
                7,
                101,
                57,
                66,
                75,
                169,
                188,
                225,
                281,
                294,
                63,
                167,
                171,
                169,
                188
            ],
            "leader": 183
        }
    },
    "defeatgames": 0,
    "drawgames": 0,
    "name": "123",
    "totalgames": 0,
    "victorygames": 0
}
